[{"size":[11,10],"data":["l4","Ma","B4","b","p4","o1","i4","b","S5","n","n","b","i4","b","t4","b","n","b","n","S5","l4","n","S5","n","S4","n","b","n","b","n","S6","b","n","b","n","n","S4","n","n","b","n","b","b","n","i4","o1","b","b","b","T9","B4","r4","o1","r4","b","f4","n","n","r4","n","n","n","b","n","n","S4","h9","b","B4","f4","B4","B4","o1","b","S6","b","f4","b","n","n","S6","t4","b","b","k1","n","n","n","t4","n","n","b","n","b","n","t4","n","n","n","s","l4","r4","r4","B4","b","b","b","n","n","n"]},{"size":[11,10],"data":["n","n","n","n","n","n","B4","r4","B4","b","n","n","n","b","r4","b","i4","f4","f4","n","b","n","n","n","B4","n","S4","n","n","b","n","B4","n","n","n","b","n","b","n","n","Ma","b","T9","B4","n","n","b","h9","r4","f4","b","i4","o1","b","n","n","n","n","n","k1","n","n","l4","n","t4","n","i4","r4","o1","S5","b","l4","t4","l4","n","b","n","p4","n","n","b","o1","b","n","S6","S6","t4","n","t4","S5","b","o1","S5","b","B4","n","n","S4","n","s","b","n","n","n","n","S4","S6","r4","b","n"]},{"size":[11,10],"data":["n","n","b","b","b","t4","b","n","n","n","n","n","n","k1","n","b","n","r4","h9","o1","S6","b","n","n","S5","n","t4","n","n","n","B4","n","i4","B4","t4","S4","b","b","b","f4","b","T9","b","r4","o1","n","S4","n","b","n","n","o1","n","r4","n","i4","B4","p4","S4","b","S5","o1","b","n","S6","n","n","b","n","n","b","n","r4","r4","b","Ma","n","n","f4","n","n","b","n","S5","B4","n","l4","n","n","b","n","n","i4","n","b","t4","n","b","n","s","b","b","S6","B4","l4","B4","f4","l4","b","n"]},{"size":[11,10],"data":["n","n","n","n","S6","t4","l4","n","n","n","n","l4","b","r4","n","Ma","i4","B4","S6","b","n","n","b","n","r4","n","b","n","b","n","t4","n","n","o1","n","S4","b","b","b","b","S5","B4","i4","n","B4","r4","b","h9","r4","n","S5","n","n","B4","n","f4","n","n","n","i4","n","f4","p4","B4","o1","n","o1","f4","S5","b","b","t4","r4","n","n","t4","n","n","l4","n","n","b","n","b","b","b","k1","n","n","B4","n","b","T9","n","o1","n","n","b","n","s","b","S4","S4","b","b","b","b","b","S6","b"]},{"size":[11,10],"data":["T9","b","p4","f4","b","b","B4","n","n","n","n","S4","n","b","n","b","n","f4","n","n","n","n","b","S6","Ma","b","t4","b","r4","S4","b","b","t4","l4","n","S5","n","b","n","b","i4","o1","n","n","S4","n","r4","B4","B4","f4","B4","S5","S5","b","b","o1","n","b","n","n","n","r4","r4","n","n","i4","b","B4","r4","S6","n","n","n","h9","t4","b","o1","n","B4","n","b","n","n","n","b","b","n","o1","b","t4","b","b","k1","l4","i4","b","l4","b","S6","s","b","n","n","n","n","n","n","n","n","n"]},{"size":[5,5],"data":["r4","e4","e4","e4","b","r4","n","n","n","B4","r4","b","Ma","n","B4","n","n","n","n","B4","s","b","k1","h7","b"]}]